ddns_python/__init__.py
ddns_python/console_menu.py
ddns_python/constants.py
ddns_python/main.py
ddns_python/test_configuration.py
ddns_python/update.py
ddns_python/utils.py
ddns_python-1.0.0.dist-info/LICENSE.md
ddns_python-1.0.0.dist-info/METADATA
ddns_python-1.0.0.dist-info/WHEEL
ddns_python-1.0.0.dist-info/entry_points.txt
ddns_python-1.0.0.dist-info/RECORD
