Metadata-Version: 2.1
Name: ddns-python
Version: 1.0.0
Summary: 
Author: 9Lukas5
Author-email: lukas.wiest@infinite-tech.solutions
Requires-Python: >=3.8,<4.0
Classifier: Programming Language :: Python :: 3
Classifier: Programming Language :: Python :: 3.8
Classifier: Programming Language :: Python :: 3.9
Classifier: Programming Language :: Python :: 3.10
Classifier: Programming Language :: Python :: 3.11
Classifier: Programming Language :: Python :: 3.12
